u3606b_py/__init__.py
u3606b_py/u3606b.py
u3606b_py-0.0.4.dist-info/LICENSE
u3606b_py-0.0.4.dist-info/METADATA
u3606b_py-0.0.4.dist-info/WHEEL
u3606b_py-0.0.4.dist-info/top_level.txt
u3606b_py-0.0.4.dist-info/RECORD
