Metadata-Version: 2.1
Name: u3606b_py
Version: 0.0.4
Summary: Control Keysight U3606B Multimeter through PyVISA
Author-email: Li Bo <libo_go@163.com>
Project-URL: Homepage, https://github.com/leeebo/u3606b_py
Project-URL: Bug Tracker, https://github.com/leeebo/u3606b_py/issues
Classifier: Programming Language :: Python :: 3
Classifier: License :: OSI Approved :: Apache Software License
Classifier: Operating System :: OS Independent
Requires-Python: >=3.8
License-File: LICENSE
Requires-Dist: pyvisa
